idspy_toolkit/__init__.py
idspy_toolkit/_version.py
idspy_toolkit/accessor.py
idspy_toolkit/constants.py
idspy_toolkit/converter.py
idspy_toolkit/exceptions.py
idspy_toolkit/simplexml.py
idspy_toolkit/snippets.py
idspy_toolkit/toolkit.py
idspy_toolkit/utils.py
idspy_toolkit-1.0.1.dist-info/licenses/LICENSE
idspy_toolkit-1.0.1.dist-info/METADATA
idspy_toolkit-1.0.1.dist-info/WHEEL
idspy_toolkit-1.0.1.dist-info/top_level.txt
idspy_toolkit-1.0.1.dist-info/RECORD
