Metadata-Version: 2.4
Name: idspy_toolkit
Version: 1.0.1
Summary: Tools to manipulate the IDSPy Dictionaries
Author-email: Guillaume Fuhr <guillaume.fuhr@univ-amu.fr>
Project-URL: Homepage, https://gitlab.com/gkdb/idspy_toolkit
Project-URL: Bug Tracker, https://gitlab.com/gkdb/idspy_toolkit/-/issues
Classifier: Development Status :: 5 - Production/Stable
Classifier: Environment :: Console
Classifier: Intended Audience :: Science/Research
Classifier: Operating System :: OS Independent
Classifier: Programming Language :: Python :: 3 :: Only
Classifier: Programming Language :: Python :: 3.9
Classifier: Programming Language :: Python :: 3.10
Classifier: Programming Language :: Python :: 3.11
Classifier: Programming Language :: Python :: 3.12
Classifier: Topic :: Scientific/Engineering
Requires-Python: >=3.9
License-File: LICENSE
Requires-Dist: idspy_dictionaries>=40000.3.0
Requires-Dist: numpy>=1.23
Requires-Dist: h5py>=3.6.0
Requires-Dist: defusedxml
Provides-Extra: test
Requires-Dist: pytest>=7.0.0; extra == "test"
Dynamic: license-file
